[
   {
        "quizId": "64e6730a80265dca5bc09236",
        "age": 4,
        "categories": "fruits",
        "state": true,
        "question": [
            {
                "questionId": "64e672bf80265dca5bc0922b",
                "title": "Question sur les fruits",
                "description": "Quel est ce fruit ?",
                "image": {
                    "_id": "64e64afe80265dca5bc091ac",
                    "type": "image",
                    "data": "",
                    "name": "Banane"
                },
                "audio": {
                    "id": "6494320737e32c916ce14047",
                    "type": "son",
                    "data": "https://drive.google.com/uc?export=download&id=1IyEybLqO73vttRjDFOOBEGNUE0TP4Ji3",
                    "name": "sans son"
                },
                "answer": [
                    {
                        "answerId": "64e671bd80265dca5bc09227",
                        "title": "Orange",
                        "description": "",
                        "isCorrect": false,
                        "image": {
                            "imageId": "64e609d080265dca5bc09168",
                            "type": "image",
                            "data": "https://github.com/medomar/json_public_data/assets/122084936/8c8afc00-9f86-4763-9c04-897af2a8edac",
                            "name": "Orange"
                        },
                        "audio": {
                            "id": "6494320737e32c916ce14047",
                            "type": "son",
                            "data": "https://drive.google.com/uc?export=download&id=1R5tKVwyM63QqkjuG6C4Y5kqtTBAuPc7K",
                            "name": "sans son"
                        }
                    },
                    {
                        "answerId": "64e671a180265dca5bc09225",
                        "title": "Melon",
                        "description": "",
                        "isCorrect": false,
                        "image": {
                            "imageId": "64e649a880265dca5bc091a8",
                            "type": "image",
                            "data": "https://github.com/medomar/json_public_data/assets/122084936/b05e890a-dfe4-479b-9aa3-844ec92e3b2b",
                            "name": "melon"
                        },
                        "audio": {
                            "id": "6494320737e32c916ce14047",
                            "type": "son",
                            "data": "https://drive.google.com/uc?export=download&id=1ofMW13Tw10brMgyeXBGunTCeQsG9hFeF",
                            "name": "sans son"
                        }
                    },
                    {
                        "answerId": "64e6718180265dca5bc09223",
                        "title": "Banane",
                        "description": "",
                        "isCorrect": true,
                        "image": {
                            "imageId": "64e64afe80265dca5bc091ac",
                            "type": "image",
                            "data": "https://github.com/medomar/json_public_data/assets/122084936/0f148878-0332-4f37-9d38-6387bf565174",
                            "name": "Banane"
                        },
                        "audio": {
                            "id": "6494320737e32c916ce14047",
                            "type": "son",
                            "data": "https://drive.google.com/uc?export=download&id=1IyEybLqO73vttRjDFOOBEGNUE0TP4Ji3",
                            "name": "sans son"
                        }
                    }
                ]
            },
            {
                "questionId": "64a299180c11a47cea2dd093",
                "title": "Question sur les fruits",
                "description": "Est-ce que tu connais ce fruit ?",
                "image": {
                    "imageId": "647f94ebcaa96ef2fc1bee25",
                    "type": "image",
                    "data": "",
                    "name": "Abricot "
                },
                "audio": {
                    "id": "6494320737e32c916ce14047",
                    "type": "son",
                    "data": "https://drive.google.com/uc?export=download&id=1Hv8kKsicBwzcrFsriLcIgDToP_R65aoB",
                    "name": "sans son"
                },
                "answer": [
                    {
                        "answerId": "64a2911a508b7f93cb450c50",
                        "title": "Ananas",
                        "description": "",
                        "isCorrect": false,
                        "image": {
                            "imageId": "64a29107508b7f93cb450c4e",
                            "type": "image",
                            "data": "https://github.com/medomar/json_public_data/assets/122084936/24ea2f12-1b61-4270-8227-5b40bc2fb7a5",
                            "name": "Ananas"
                        },
                        "audio": {
                            "id": "6494320737e32c916ce14047",
                            "type": "son",
                            "data": "https://drive.google.com/uc?export=download&id=1bREIWTyaMk4foQsVoBwWOO8-VtRTQWI9",
                            "name": "sans son"
                        }
                    },
                    {
                        "answerId": "64a29080508b7f93cb450c4c",
                        "title": "Abricot",
                        "description": "",
                        "isCorrect": true,
                        "image": {
                            "imageId": "647f94ebcaa96ef2fc1bee25",
                            "type": "image",
                            "data": "https://github.com/medomar/json_public_data/assets/122084936/fcea1640-6e1e-451a-be88-3af546709617",
                            "name": "Abricot "
                        },
                        "audio": {
                            "id": "6494320737e32c916ce14047",
                            "type": "son",
                            "data": "https://drive.google.com/uc?export=download&id=1Hv8kKsicBwzcrFsriLcIgDToP_R65aoB",
                            "name": "sans son"
                        }
                    },
                    {
                        "answerId": "64a2905c508b7f93cb450c49",
                        "title": "cerise",
                        "description": "",
                        "isCorrect": false,
                        "image": {
                            "imageId": "6486ec2584e0fd8a919c9f29",
                            "type": "image",
                            "data": "https://github.com/medomar/json_public_data/assets/122084936/03e4ef83-2e3a-4583-b2c6-4a93c9836628",
                            "name": "cerise"
                        },
                        "audio": {
                            "id": "6494320737e32c916ce14047",
                            "type": "son",
                            "data": "https://drive.google.com/uc?export=download&id=1DSBwH3uNhYbSjS3itbOz0OLuX0EB0vRZ",
                            "name": "sans son"
                        }
                    }
                ]
            },
            {
            "questionId": "65f78e284a3a9c000f424688",
            "title": "Question sur les fruits",
            "description": "Identifie ce fruit.",
            "image": {
                "imageId": "65f78e284a3a9c000f42468a",
                "type": "image",
                "data": "https://github.com/medomar/json_public_data/assets/122084936/65af67d8-5566-43ee-9a32-119aef67b54b",
                "name": "Fraise"
            },
            "audio": {
                "_id": "65f78e284a3a9c000f42468b",
                "type": "son",
                "data": "Lien audio pour la fraise",
                "name": "sans son"
            },
            "answer": [
                {
                    "answerId": "65f78e284a3a9c000f42468c",
                    "title": "Pomme",
                    "description": "",
                    "isCorrect": false,
                    "image": {
                        "imageId": "65f78e284a3a9c000f42468d",
                        "type": "image",
                        "data": "https://github.com/medomar/json_public_data/assets/122084936/68b3e3bf-fe4f-46fd-9a4d-b3613d3df8e7",
                        "name": "Pomme"
                    },
                    "audio": {
                        "id": "65f78e284a3a9c000f42468e",
                        "type": "son",
                        "data": "Lien audio pour la pomme",
                        "name": "sans son"
                    }
                },
                {
                    "answerId": "65f78e284a3a9c000f42468f",
                    "title": "Fraise",
                    "description": "",
                    "isCorrect": true,
                    "image": {
                        "imageId": "65f78e284a3a9c000f424690",
                        "type": "image",
                        "data": "https://github.com/medomar/json_public_data/assets/122084936/65af67d8-5566-43ee-9a32-119aef67b54b",
                        "name": "Fraise"
                    },
                    "audio": {
                        "id": "65f78e284a3a9c000f424691",
                        "type": "son",
                        "data": "Lien audio pour la fraise",
                        "name": "sans son"
                    }
                },
                {
                    "answerId": "65f78e284a3a9c000f424692",
                    "title": "Poire",
                    "description": "",
                    "isCorrect": false,
                    "image": {
                        "imageId": "65f78e284a3a9c000f424693",
                        "type": "image",
                        "data": "https://github.com/medomar/json_public_data/assets/122084936/a6787d22-1038-4489-9f20-2d4acf243d06",
                        "name": "Poire"
                    },
                    "audio": {
                        "id": "65f78e284a3a9c000f424694",
                        "type": "son",
                        "data": "Lien audio pour la poire",
                        "name": "sans son"
                    }
                }
            ]
        },
        {
            "questionId": "65f78e284a3a9c000f424695",
            "title": "Question sur les fruits",
            "description": "Peux-tu trouver ce fruit ?",
            "image": {
                "id": "65f78e284a3a9c000f424696",
                "type": "image",
                "data": "https://github.com/medomar/json_public_data/assets/122084936/05acec99-5718-4319-b5f8-47c216913569",
                "name": "Pastèque"
            },
            "audio": {
                "id": "65f78e284a3a9c000f424697",
                "type": "son",
                "data": "Lien audio pour la pastèque",
                "name": "sans son"
            },
            "answer": [
                {
                    "answerId": "65f78e284a3a9c000f424698",
                    "title": "Banane",
                    "description": "",
                    "isCorrect": false,
                    "image": {
                        "imageId": "65f78e284a3a9c000f424699",
                        "type": "image",
                        "data": "https://github.com/medomar/json_public_data/assets/122084936/31a34df8-9f4c-4af1-88fe-e53b522b9300",
                        "name": "Banane"
                    },
                    "audio": {
                        "id": "65f78e284a3a9c000f42469a",
                        "type": "son",
                        "data": "Lien audio pour la banane",
                        "name": "sans son"
                    }
                },
                {
                    "answerId": "65f78e284a3a9c000f42469b",
                    "title": "Pêche",
                    "description": "",
                    "isCorrect": false,
                    "image": {
                        "imageId": "65f78e284a3a9c000f42469c",
                        "type": "image",
                        "data": "https://github.com/medomar/json_public_data/assets/122084936/37248704-28e8-4ccc-9cc2-d0941795b4d9",
                        "name": "Pêche"
                    },
                    "audio": {
                        "id": "65f78e284a3a9c000f42469d",
                        "type": "son",
                        "data": "Lien audio pour la pêche",
                        "name": "sans son"
                    }
                },
                {
                    "answerId": "65f78e284a3a9c000f42469e",
                    "title": "Pastèque",
                    "description": "",
                    "isCorrect": true,
                    "image": {
                        "imageId": "65f78e284a3a9c000f42469f",
                        "type": "image",
                        "data": "https://github.com/medomar/json_public_data/assets/122084936/05acec99-5718-4319-b5f8-47c216913569",
                        "name": "Pastèque"
                    },
                    "audio": {
                        "id": "65f78e284a3a9c000f4246a0",
                        "type": "son",
                        "data": "Lien audio pour la pastèque",
                        "name": "sans son"
                    }
                }
            ]
        }
      ]
    },
     {
        "quizId": "64a2a3b40c11a47cea2dd0c8",
        "age": 5,
        "categories": "légumes",
        "state": true,
        "question": [
            {
                "questionId": "64a2a1a50c11a47cea2dd0b4",
                "title": "Question sur les légumes",
                "description": "Est-ce que tu connais ce légume ??",
                "image": {
                    "imageId": "647f0937caa96ef2fc1bec6d",
                    "type": "image",
                    "data": "",
                    "name": "Pomme de terre"
                },
                "audio": {
                    "id": "6494320737e32c916ce14047",
                    "type": "son",
                    "data": "https://drive.google.com/uc?export=download&id=1UF-vgqh1yd4oRR_dxwgGszyjqX7mcWCN",
                    "name": "sans son"
                },
                "answer": [
                    {
                        "answerId": "64a29e590c11a47cea2dd0ac",
                        "title": "Citrouille",
                        "description": "",
                        "isCorrect": false,
                        "image": {
                            "imageId": "64a29c7f0c11a47cea2dd0a2",
                            "type": "image",
                            "data": "https://github.com/medomar/json_public_data/assets/122084936/32224b44-5d6c-4672-9f9b-993b4390136e",
                            "name": "Citrouille "
                        },
                        "audio": {
                            "imageId": "6494320737e32c916ce14047",
                            "type": "son",
                            "data": "https://drive.google.com/uc?export=download&id=1UBSVF2sluR1Gc7ZWo1kPWndhcCrVHquO",
                            "name": "sans son"
                        }
                    },
                    {
                        "answerId": "64a29ded0c11a47cea2dd0a9",
                        "title": "Chou-fleur",
                        "description": "",
                        "isCorrect": false,
                        "image": {
                            "imageId": "64a29d4d0c11a47cea2dd0a4",
                            "type": "image",
                            "data": "https://github.com/medomar/json_public_data/assets/122084936/44a1b9f3-be83-4ea6-a17f-894872af31ac",
                            "name": "Chou-fleur "
                        },
                        "audio": {
                            "id": "6494320737e32c916ce14047",
                            "type": "son",
                            "data": "https://drive.google.com/uc?export=download&id=1Bha7Swl_Y0h5cTnlvesSC0H_X18jkCv2",
                            "name": "sans son"
                        }
                    },
                    {
                        "answerId": "64a29b720c11a47cea2dd09e",
                        "title": "Pomme de terre",
                        "description": "La pomme de terre est un légume rond et délicieux. Elle pousse sous la terre et peut être brune, jaune ou violette à l'extérieur. À l'intérieur, elle est blanche ou jaune pâle. On peut la cuisiner de différentes façons, comme des frites ou de la purée. La pomme de terre est bonne pour notre corps car elle contient des vitamines et des minéraux. C'est un légume spécial et savoureux !",
                        "isCorrect": true,
                        "image": {
                            "imageId": "647f0937caa96ef2fc1bec6d",
                            "type": "image",
                            "data": "https://github.com/medomar/json_public_data/assets/122084936/1a30edcf-9e53-49d7-8615-b71e8c4a6a21",
                            "name": "Pomme de terre"
                        },
                        "audio": {
                            "id": "6494320737e32c916ce14047",
                            "type": "son",
                            "data": "https://drive.google.com/uc?export=download&id=1UF-vgqh1yd4oRR_dxwgGszyjqX7mcWCN",
                            "name": "sans son"
                        }
                    }
                ]
            },
            {
                "questionId": "64e63ae980265dca5bc09191",
                "title": "Question sur les légumes",
                "description": "Reconnais-tu ce légume ?",
                "image": {
                    "imageId": "64e609fa80265dca5bc0916a",
                    "type": "image",
                    "data": "",
                    "name": "Ognions"
                },
                "audio": {
                    "id": "6494320737e32c916ce14047",
                    "type": "son",
                    "data": "",
                    "name": "sans son"
                },
                "answer": [
                    {
                        "answerId": "64e62ab180265dca5bc09175",
                        "title": "Citrouille",
                        "description": "",
                        "isCorrect": false,
                        "image": {
                            "imageId": "64a29c7f0c11a47cea2dd0a2",
                            "type": "image",
                            "data": "https://github.com/medomar/json_public_data/assets/122084936/32224b44-5d6c-4672-9f9b-993b4390136e",
                            "name": "Citrouille "
                        },
                        "audio": {
                            "id": "6494320737e32c916ce14047",
                            "type": "son",
                            "data": "https://drive.google.com/file/d/1UBSVF2sluR1Gc7ZWo1kPWndhcCrVHquO/view?usp=drive_link",
                            "name": "sans son"
                        }
                    },
                    {
                        "answerId": "64e629c180265dca5bc09173",
                        "title": "Carotte",
                        "description": "",
                        "isCorrect": false,
                        "image": {
                            "imageId": "64e607d380265dca5bc09156",
                            "type": "image",
                            "data": "https://github.com/medomar/json_public_data/assets/122084936/c564bc0b-5ccb-4b56-a5e4-afa00c70b5d9",
                            "name": "Carotte "
                        },
                        "audio": {
                            "id": "6494320737e32c916ce14047",
                            "type": "son",
                            "data": "https://drive.google.com/uc?export=download&id=1h_VKcM1hcXQ_7EwqVo_rvdXHOd-X_S1N",
                            "name": "sans son"
                        }
                    },
                    {
                        "answerId": "64e625f380265dca5bc0916f",
                        "title": "Ognions",
                        "description": "",
                        "isCorrect": true,
                        "image": {
                            "imageId": "64e609fa80265dca5bc0916a",
                            "type": "image",
                            "data": "https://github.com/medomar/json_public_data/assets/122084936/69d0f538-113f-4565-989a-36d4e0dfd47d",
                            "name": "Ognions"
                        },
                        "audio": {
                            "id": "6494320737e32c916ce14047",
                            "type": "son",
                            "data": "https://drive.google.com/uc?export=download&id=1ioycReYmYo3FniTK0pZnZyTjZOaGdBKx",
                            "name": "sans son"
                        }
                    }
                ]
            },
            {
            "questionId": "65f78e284a3a9c000f4246a2",
            "title": "Question sur les légumes",
            "description": "Identifie ce légume.",
            "image": {
                "imageId": "65f78e284a3a9c000f4246a3",
                "type": "image",
                "data": "https://github.com/medomar/json_public_data/assets/122084936/332b0da4-d0b8-4a30-9d80-59d471f6bac3",
                "name": "Carotte"
            },
            "audio": {
                "id": "65f78e284a3a9c000f4246a4",
                "type": "son",
                "data": "Lien audio pour la carotte",
                "name": "sans son"
            },
            "answer": [
                {
                    "answerId": "65f78e284a3a9c000f4246a5",
                    "title": "Tomate",
                    "description": "",
                    "isCorrect": false,
                    "image": {
                        "imageId": "65f78e284a3a9c000f4246a6",
                        "type": "image",
                        "data": "https://github.com/medomar/json_public_data/assets/122084936/e464357b-3f61-435c-acda-e69c41dfab42",
                        "name": "Tomate"
                    },
                    "audio": {
                        "id": "65f78e284a3a9c000f4246a7",
                        "type": "son",
                        "data": "Lien audio pour la tomate",
                        "name": "sans son"
                    }
                },
                {
                    "answerId": "65f78e284a3a9c000f4246a8",
                    "title": "Carotte",
                    "description": "",
                    "isCorrect": true,
                    "image": {
                        "imageId": "65f78e284a3a9c000f4246a9",
                        "type": "image",
                        "data": "https://github.com/medomar/json_public_data/assets/122084936/332b0da4-d0b8-4a30-9d80-59d471f6bac3",
                        "name": "Carotte"
                    },
                    "audio": {
                        "id": "65f78e284a3a9c000f4246aa",
                        "type": "son",
                        "data": "Lien audio pour la carotte",
                        "name": "sans son"
                    }
                },
                {
                    "answerId": "65f78e284a3a9c000f4246ab",
                    "title": "Aubergine",
                    "description": "",
                    "isCorrect": false,
                    "image": {
                        "imageId": "65f78e284a3a9c000f4246ac",
                        "type": "image",
                        "data": "https://github.com/medomar/json_public_data/assets/122084936/238dadc5-abde-4881-9e3c-ff05c369c3fc",
                        "name": "Aubergine"
                    },
                    "audio": {
                        "id": "65f78e284a3a9c000f4246ad",
                        "type": "son",
                        "data": "Lien audio pour l'aubergine",
                        "name": "sans son"
                    }
                }
            ]
        },
            {
            "questionId": "65f78e284a3a9c000f4246ae",
            "title": "Question sur les légumes",
            "description": "Peux-tu trouver ce légume ?",
            "image": {
                "imageId": "65f78e284a3a9c000f4246af",
                "type": "image",
                "data": "https://github.com/medomar/json_public_data/assets/122084936/54095dc2-d301-4a11-9ed3-447738940e0b",
                "name": "Concombre"
            },
            "audio": {
                "id": "65f78e284a3a9c000f4246b0",
                "type": "son",
                "data": "Lien audio pour le concombre",
                "name": "sans son"
            },
            "answer": [
                {
                    "answerId": "65f78e284a3a9c000f4246b1",
                    "title": "Pomme de terre",
                    "description": "",
                    "isCorrect": false,
                    "image": {
                        "imageId": "65f78e284a3a9c000f4246b2",
                        "type": "image",
                        "data": "https://github.com/medomar/json_public_data/assets/122084936/dab83706-884a-4674-91a5-77a97a62abe1",
                        "name": "Pomme de terre"
                    },
                    "audio": {
                        "id": "65f78e284a3a9c000f4246b3",
                        "type": "son",
                        "data": "Lien audio pour la pomme de terre",
                        "name": "sans son"
                    }
                },
                {
                    "answerId": "65f78e284a3a9c000f4246b4",
                    "title": "Concombre",
                    "description": "",
                    "isCorrect": true,
                    "image": {
                        "imageId": "65f78e284a3a9c000f4246b5",
                        "type": "image",
                        "data": "https://github.com/medomar/json_public_data/assets/122084936/54095dc2-d301-4a11-9ed3-447738940e0b",
                        "name": "Concombre"
                    },
                    "audio": {
                        "id": "65f78e284a3a9c000f4246b6",
                        "type": "son",
                        "data": "Lien audio pour le concombre",
                        "name": "sans son"
                    }
                },
                {
                    "answerId": "65f78e284a3a9c000f4246b7",
                    "title": "Courgette",
                    "description": "",
                    "isCorrect": false,
                    "image": {
                        "imageId": "65f78e284a3a9c000f4246b8",
                        "type": "image",
                        "data": "https://github.com/medomar/json_public_data/assets/122084936/c4990f92-9b2b-41c1-a96f-c67307fd0b8e",
                        "name": "Courgette"
                    },
                    "audio": {
                        "id": "65f78e284a3a9c000f4246b9",
                        "type": "son",
                        "data": "Lien audio pour la courgette",
                        "name": "sans son"
                    }
                }
            ]
        }
        ]
    },
      {
              "quizId": "64e6612e80265dca5bc091ff",
               "age": 7,
               "categories": "animal",
               "state": true,
               "question": 
                           [
                             {
        "questionId": "64e6611180265dca5bc091fd",
        "title": "Question sur les Animaux",
        "description": "Reconnaissez-vous cet animal ?",
        "image": {
            "imageId": "64e64e3980265dca5bc091b1",
            "type": "image",
            "data": "https://github.com/medomar/json_public_data/assets/122084936/b147c4a5-b74f-477b-a639-c15282c915d6",
            "name": "Canard"
        },
        "audio": {
            "id": "6494320737e32c916ce14047",
            "type": "son",
            "data": "https://drive.google.com/uc?export=download&id=1v_g4kSvIfOqCwVccF0AFQ7l9FBsOa7mD",
            "name": "sans son"
        },
        "answer": [
            {
                "answerId": "64e6600b80265dca5bc091f5",
                "title": "Canard",
                "description": "",
                "isCorrect": true,
                "image": {
                    "imageId": "64e64e3980265dca5bc091b1",
                    "type": "image",
                    "data": "https://github.com/medomar/json_public_data/assets/122084936/b147c4a5-b74f-477b-a639-c15282c915d6",
                    "name": "Canard"
                },
                "audio": {
                    "id": "6494320737e32c916ce14047",
                    "type": "son",
                    "data": "https://drive.google.com/uc?export=download&id=1v_g4kSvIfOqCwVccF0AFQ7l9FBsOa7mD",
                    "name": "Canard Sound"
                }
            },
            {
                "answerId": "64e6606f80265dca5bc091f7",
                "title": "Coq",
                "description": "",
                "isCorrect": false,
                "image": {
                    "imageId": "6486ec6c84e0fd8a919c9f36",
                    "type": "image",
                    "data": "https://github.com/medomar/json_public_data/assets/122084936/a51f8e4b-7068-45c4-a845-f74ba5a108fa",
                    "name": "Coq"
                },
                "audio": {
                    "id": "6494320737e32c916ce14047",
                    "type": "son",
                    "data": "https://drive.google.com/uc?export=download&id=1tCgsBCHmSPxrnv-vZd2BKGvWL9gndR1h",
                    "name": "Coq Sound"
                }
            },
            {
                "answerId": "64e6609980265dca5bc091f9",
                "title": "rat",
                "description": "",
                "isCorrect": false,
                "image": {
                    "imageId": "64e64e8680265dca5bc091b7",
                    "type": "image",
                    "data": "https://github.com/medomar/json_public_data/assets/122084936/d7084721-98d1-43c8-ad93-350a70c7b6a4",
                    "name": "rat"
                },
                "audio": {
                    "id": "6494320737e32c916ce14047",
                    "type": "son",
                    "data": "https://drive.google.com/uc?export=download&id=1I-SxOhyo9bx76cyYOL3bFOExgZBa2OZG",
                    "name": "Rat Sound"
                }
            }
        ],
        "__v": 0
    },
    {
        "questionId": "64e6611180265dca5bc091fb",
        "title": "Question sur les Animaux",
        "description": "Reconnaissez-vous cet animal ?",
        "image": {
            "imageId": "64e64e3980265dca5bc091b9",
            "type": "image",
            "data": "https://github.com/medomar/json_public_data/assets/122084936/e79ee1e4-13e2-4c87-a46e-f7745f394a0a",
            "name": "Tigre"
        },
        "audio": {
            "id": "6494320737e32c916ce14048",
            "type": "son",
            "data": "https://drive.google.com/uc?export=download&id=1v_g4kSvIfOqCwVccF0AFQ7l9FBsOa7mD",
            "name": "sans son"
        },
        "answer": [
            {
                "answerId": "64e6600b80265dca5bc091f0",
                "title": "Tigre",
                "description": "",
                "isCorrect": true,
                "image": {
                    "imageId": "64e64e3980265dca5bc091b8",
                    "type": "image",
                    "data": "https://github.com/medomar/json_public_data/assets/122084936/e79ee1e4-13e2-4c87-a46e-f7745f394a0a",
                    "name": "Tigre"
                },
                "audio": {
                    "imageId": "6494320737e32c916ce14048",
                    "type": "son",
                    "data": "https://drive.google.com/uc?export=download&id=1v_g4kSvIfOqCwVccF0AFQ7l9FBsOa7mD",
                    "name": "Canard Sound"
                }
            },
            {
                "answerId": "64e6606f80265dca5bc091f0",
                "title": "Lapin",
                "description": "",
                "isCorrect": false,
                "image": {
                    "imageId": "6486ec6c84e0fd8a919c9f3i",
                    "type": "image",
                    "data": "https://github.com/medomar/json_public_data/assets/122084936/3ca7d306-d480-4059-84a4-237e38a711fd",
                    "name": "Lapin"
                },
                "audio": {
                    "id": "6494320737e32c916ce14040",
                    "type": "son",
                    "data": "https://drive.google.com/uc?export=download&id=1tCgsBCHmSPxrnv-vZd2BKGvWL9gndR1h",
                    "name": "Coq Sound"
                }
            },
            {
                "answerId": "64e6609980265dca5bc091f0",
                "title": "cheval",
                "description": "",
                "isCorrect": false,
                "image": {
                    "imageId": "64e64e8680265dca5bc091b8",
                    "type": "image",
                    "data": "https://github.com/medomar/json_public_data/assets/122084936/8bd7c080-775d-4aed-b5fb-358d9877bece",
                    "name": "cheval"
                },
                "audio": {
                    "id": "6494320737e32c916ce14040",
                    "type": "son",
                    "data": "https://drive.google.com/uc?export=download&id=1I-SxOhyo9bx76cyYOL3bFOExgZBa2OZG",
                    "name": "Rat Sound"
                }
            }
        ],
        "__v": 0
    },
    {
            "questionId": "65f78e284a3a9c000f4246bb",
            "title": "Question sur les animaux",
            "description": "Identifie cet animal.",
            "image": {
                "imageId": "65f78e284a3a9c000f4246bc",
                "type": "image",
                "data": "https://github.com/medomar/json_public_data/assets/122084936/10f5f89f-9170-448d-94e9-dc53b17d6f61",
                "name": "Chien"
            },
            "audio": {
                "id": "65f78e284a3a9c000f4246bd",
                "type": "son",
                "data": "Lien audio pour le chien",
                "name": "sans son"
            },
            "answer": [
                {
                    "answerId": "65f78e284a3a9c000f4246be",
                    "title": "Chat",
                    "description": "",
                    "isCorrect": false,
                    "image": {
                        "imageId": "65f78e284a3a9c000f4246bf",
                        "type": "image",
                        "data": "https://github.com/medomar/json_public_data/assets/122084936/79edd0e4-597f-4fc5-aa42-a98a6524c0eb",
                        "name": "Chat"
                    },
                    "audio": {
                        "id": "65f78e284a3a9c000f4246c0",
                        "type": "son",
                        "data": "Lien audio pour le chat",
                        "name": "sans son"
                    }
                },
                {
                    "answerId": "65f78e284a3a9c000f4246c1",
                    "title": "Chien",
                    "description": "",
                    "isCorrect": true,
                    "image": {
                        "imageId": "65f78e284a3a9c000f4246c2",
                        "type": "image",
                        "data": "https://github.com/medomar/json_public_data/assets/122084936/10f5f89f-9170-448d-94e9-dc53b17d6f61",
                        "name": "Chien"
                    },
                    "audio": {
                        "id": "65f78e284a3a9c000f4246c3",
                        "type": "son",
                        "data": "Lien audio pour le chien",
                        "name": "sans son"
                    }
                },
                {
                    "answerId": "65f78e284a3a9c000f4246c4",
                    "title": "Lion",
                    "description": "",
                    "isCorrect": false,
                    "image": {
                        "imageId": "65f78e284a3a9c000f4246c5",
                        "type": "image",
                        "data": "https://github.com/medomar/json_public_data/assets/122084936/dc491715-e2ef-4387-93bb-3831e5bbe1de",
                        "name": "Lion"
                    },
                    "audio": {
                        "id": "65f78e284a3a9c000f4246c6",
                        "type": "son",
                        "data": "Lien audio pour le lion",
                        "name": "sans son"
                    }
                }
            ]
        },
    {
            "questionId": "65f78e284a3a9c000f4246c7",
            "title": "Question sur les animaux",
            "description": "Peux-tu trouver cet animal ?",
            "image": {
                "imageId": "65f78e284a3a9c000f4246c8",
                "type": "image",
                "data": "https://github.com/medomar/json_public_data/assets/122084936/c59cadeb-0bb7-4f31-aec2-24094dea5dbc",
                "name": "Éléphant"
            },
            "audio": {
                "id": "65f78e284a3a9c000f4246c9",
                "type": "son",
                "data": "Lien audio pour l'éléphant",
                "name": "sans son"
            },
            "answer": [
                {
                    "answerId": "65f78e284a3a9c000f4246ca",
                    "title": "Girafe",
                    "description": "",
                    "isCorrect": false,
                    "image": {
                        "imageId": "65f78e284a3a9c000f4246cb",
                        "type": "image",
                        "data": "https://github.com/medomar/json_public_data/assets/122084936/965299b5-6c66-4e3a-a56a-6acd718f8cb2",
                        "name": "Girafe"
                    },
                    "audio": {
                        "id": "65f78e284a3a9c000f4246cc",
                        "type": "son",
                        "data": "Lien audio pour la girafe",
                        "name": "sans son"
                    }
                },
                {
                    "answerId": "65f78e284a3a9c000f4246cd",
                    "title": "Éléphant",
                    "description": "",
                    "isCorrect": true,
                    "image": {
                        "imageId": "65f78e284a3a9c000f4246ce",
                        "type": "image",
                        "data": "https://github.com/medomar/json_public_data/assets/122084936/c59cadeb-0bb7-4f31-aec2-24094dea5dbc",
                        "name": "Éléphant"
                    },
                    "audio": {
                        "id": "65f78e284a3a9c000f4246cf",
                        "type": "son",
                        "data": "Lien audio pour l'éléphant",
                        "name": "sans son"
                    }
                },
                {
                    "answerId": "65f78e284a3a9c000f4246d0",
                    "title": "Zèbre",
                    "description": "",
                    "isCorrect": false,
                    "image": {
                        "imageId": "65f78e284a3a9c000f4246d1",
                        "type": "image",
                        "data": "https://github.com/medomar/json_public_data/assets/122084936/a846af2f-b51b-49ca-ba6e-d563ab2b84a9",
                        "name": "Zèbre"
                    },
                    "audio": {
                        "id": "65f78e284a3a9c000f4246d2",
                        "type": "son",
                        "data": "Lien audio pour le zèbre",
                        "name": "sans son"
                    }
                }
            ]
        }

    ]
}
]
